{
  "title": {
    "en": "It !{{is|isn't}} going to rain in..."
  },
  "titleFormatted": {
    "en": "It !{{is|isn't}} going to rain in [[when]]"
  },
  "hint": {
    "en": "Checks if it will/will not rain more than 0.1 mm/h within the given amount of time."
  },
  "args": [
    {
      "name": "when",
      "type": "dropdown",
      "values": [
        {
          "id": "5",
          "label": {
            "en": "5 minutes"
          }
        },
        {
          "id": "10",
          "label": {
            "en": "10 minutes"
          }
        },
        {
          "id": "15",
          "label": {
            "en": "15 minutes"
          }
        }
      ]
    }
  ]
}